setup.py
highlights/__init__.py
highlights.egg-info/PKG-INFO
highlights.egg-info/SOURCES.txt
highlights.egg-info/dependency_links.txt
highlights.egg-info/requires.txt
highlights.egg-info/top_level.txt
highlights/evaluate/__init__.py
highlights/evaluate/rouge.py
highlights/extractive/__init__.py
highlights/extractive/erank.py
highlights/extractive/textrank.py
highlights/extractive/tgraph.py
highlights/internals/__init__.py
highlights/internals/graph.py
highlights/internals/helpers.py
highlights/internals/pagerank.py