Metadata-Version: 1.1
Name: highlights
Version: 0.1.1
Summary: A Python 3 package for automatic summarization
Home-page: https://github.com/cristiandima/highlights
Author: Cristian Dima
Author-email: UNKNOWN
License: MIT
Keywords: text summarization key sentences extraction
Platform: UNKNOWN
Classifier: Development Status :: 5 - Production/Stable
Classifier: Intended Audience :: Developers
Classifier: License :: OSI Approved :: MIT License
Classifier: Programming Language :: Python :: 3.5
